{
  "version": "1.0.0",
  "label": "LED Magic Mushroom",
  "manufacturer": "Varytec",
  "bulb_type": "LED",
  "bulb_lumens": 0,
  "bulb_color_temperature": 0,
  "dimension_weight": 5,
  "dimension_width": 406,
  "dimension_height": 279,
  "dimension_depth": 279,
  "lens_label": "Other",
  "lens_degree_min": 70,
  "lens_degree_max": 70,
  "focus_type": "Fixed",
  "focus_pan_max": 0,
  "focus_tilt_max": 0,
  "technical_power_consumption": 30,
  "technical_dmx_connector": "3-pin",
  "type": 3,
  "channels": [
    {
      "index": 0,
      "type": 0,
      "type_description": "Blue",
      "capabilities": []
    },
    {
      "index": 1,
      "type": 0,
      "type_description": "Red",
      "capabilities": []
    },
    {
      "index": 2,
      "type": 0,
      "type_description": "Green",
      "capabilities": []
    },
    {
      "index": 3,
      "type": 21,
      "type_description": "Stroboscope rate",
      "capabilities": [
        {
          "label": "0 Hz - 20 Hz",
          "min": 0,
          "max": 255
        }
      ]
    }
  ],
  "filePath": "./assets/fixtures/Varytec/Varytec-LED-Magic-Mushroom.json",
  "id": 1511
}