{
  "version": "1.0.0",
  "label": "NH-30 MK2",
  "manufacturer": "Eurolite",
  "bulb_type": "",
  "bulb_lumens": 0,
  "bulb_color_temperature": 0,
  "dimension_weight": 3,
  "dimension_width": 200,
  "dimension_height": 230,
  "dimension_depth": 370,
  "lens_label": "Other",
  "lens_degree_min": 0,
  "lens_degree_max": 0,
  "focus_type": "Fixed",
  "focus_pan_max": 0,
  "focus_tilt_max": 0,
  "technical_power_consumption": 720,
  "technical_dmx_connector": "3-pin",
  "type": 6,
  "channels": [],
  "filePath": "./assets/fixtures/Eurolite/Eurolite-NH-30-MK2.json",
  "id": 741
}